senfenico/__init__.py
senfenico/_balance.py
senfenico/_charge.py
senfenico/_checkout.py
senfenico/_settlement.py
senfenico/_transfer.py
senfenico/_webhook.py
senfenico/utils.py
senfenico-0.3.0.dist-info/METADATA
senfenico-0.3.0.dist-info/WHEEL
senfenico-0.3.0.dist-info/top_level.txt
senfenico-0.3.0.dist-info/RECORD
