Metadata-Version: 2.1
Name: senfenico
Version: 0.3.0
Summary: Python bindings for the Senfenico API
Home-page: https://github.com/senfenico/senfenico-python
Author: Senfenico
Author-email: contact@senfenico.com
License: MIT
Project-URL: Bug Tracker, https://github.com/senfenico/senfenico-python/issues
Project-URL: Documentation, https://docs.senfenico.com/en/
Project-URL: Source Code, https://github.com/senfenico/senfenico-python
Keywords: Senfenenico api payments
Requires-Dist: requests
